monday/__init__.py
monday/client.py
monday/config.py
monday/exceptions.py
monday/http_adapters.py
monday/logging_utils.py
monday/protocols.py
monday/sync_client.py
monday/fields/__init__.py
monday/fields/base_fields.py
monday/fields/board_fields.py
monday/fields/column_fields.py
monday/fields/group_fields.py
monday/fields/item_fields.py
monday/fields/user_fields.py
monday/fields/webhook_fields.py
monday/services/__init__.py
monday/services/boards.py
monday/services/groups.py
monday/services/items.py
monday/services/subitems.py
monday/services/users.py
monday/services/webhooks.py
monday/services/utils/__init__.py
monday/services/utils/data_modifiers.py
monday/services/utils/error_handlers.py
monday/services/utils/fields.py
monday/services/utils/pagination.py
monday/services/utils/query_builder.py
monday/types/__init__.py
monday/types/account.py
monday/types/asset.py
monday/types/board.py
monday/types/column.py
monday/types/column_defaults.py
monday/types/column_inputs.py
monday/types/country_codes.py
monday/types/group.py
monday/types/item.py
monday/types/subitem.py
monday/types/tag.py
monday/types/team.py
monday/types/update.py
monday/types/user.py
monday/types/webhook.py
monday/types/workspace.py
monday_client-0.1.87.dist-info/licenses/LICENSE
monday_client-0.1.87.dist-info/METADATA
monday_client-0.1.87.dist-info/WHEEL
monday_client-0.1.87.dist-info/top_level.txt
monday_client-0.1.87.dist-info/RECORD
