Metadata-Version: 2.4
Name: monday-client
Version: 0.1.87
Summary: Python library for interacting with the monday.com API. Respects monday.com API rate limits and query complexity limits.
Author-email: Dan Hollis <dh@leetsys.com>
License-Expression: GPL-3.0-only
Project-URL: Homepage, https://github.com/LeetCyberSecurity/monday-client
Project-URL: Documentation, https://monday-client.readthedocs.io/
Project-URL: Bug Reports, https://github.com/LeetCyberSecurity/monday-client/issues
Project-URL: Source, https://github.com/LeetCyberSecurity/monday-client
Keywords: monday,monday.com,api,client,async,rate-limiting,complexity-limiting
Classifier: Development Status :: 3 - Alpha
Classifier: Intended Audience :: Developers
Classifier: Programming Language :: Python :: 3
Classifier: Programming Language :: Python :: 3.12
Classifier: Topic :: Software Development :: Libraries :: Python Modules
Requires-Python: >=3.12
License-File: LICENSE
Requires-Dist: aiohttp
Provides-Extra: dev
Requires-Dist: basedpyright; extra == "dev"
Requires-Dist: doc8; extra == "dev"
Requires-Dist: esbonio; extra == "dev"
Requires-Dist: myst-parser; extra == "dev"
Requires-Dist: sphinx; extra == "dev"
Requires-Dist: sphinx-autodoc-typehints; extra == "dev"
Requires-Dist: sphinx-rtd-theme; extra == "dev"
Requires-Dist: pre-commit; extra == "dev"
Requires-Dist: pytest; extra == "dev"
Requires-Dist: pytest-asyncio; extra == "dev"
Requires-Dist: pytest-cov; extra == "dev"
Requires-Dist: pytest-mock; extra == "dev"
Requires-Dist: pyyaml; extra == "dev"
Requires-Dist: rstcheck[sphinx,toml]; extra == "dev"
Requires-Dist: ruff; extra == "dev"
Provides-Extra: proxy
Requires-Dist: aiohttp-socks; extra == "proxy"
Provides-Extra: httpx
Requires-Dist: httpx[socks]; extra == "httpx"
Requires-Dist: httpx-ntlm; extra == "httpx"
Requires-Dist: pyspnego; extra == "httpx"
Provides-Extra: yaml
Requires-Dist: pyyaml; extra == "yaml"
Dynamic: license-file
